pykbtcal/__init__.py
pykbtcal/datasets.py
pykbtcal-2.2.dist-info/LICENSE.txt
pykbtcal-2.2.dist-info/METADATA
pykbtcal-2.2.dist-info/WHEEL
pykbtcal-2.2.dist-info/top_level.txt
pykbtcal-2.2.dist-info/RECORD
